modular_cli/__init__.py
modular_cli/modular_cli.py
modular_cli/root_commands.json
modular_cli/version.py
modular_cli/modular_cli_autocomplete/__init__.py
modular_cli/modular_cli_autocomplete/complete_handler.py
modular_cli/modular_cli_autocomplete/modular_cli_complete.py
modular_cli/service/__init__.py
modular_cli/service/adapter_client.py
modular_cli/service/config.py
modular_cli/service/decorators.py
modular_cli/service/help_client.py
modular_cli/service/initializer.py
modular_cli/service/request_processor.py
modular_cli/service/utils.py
modular_cli/utils/__init__.py
modular_cli/utils/exceptions.py
modular_cli/utils/logger.py
modular_cli/utils/variables.py
modular_cli-2.3.17.dist-info/licenses/LICENSE
modular_cli-2.3.17.dist-info/METADATA
modular_cli-2.3.17.dist-info/WHEEL
modular_cli-2.3.17.dist-info/entry_points.txt
modular_cli-2.3.17.dist-info/top_level.txt
modular_cli-2.3.17.dist-info/RECORD
