Metadata-Version: 2.4
Name: modular-cli
Version: 2.3.17
Summary: Dynamic CLI for modular-api
Requires-Python: >=3.10
License-File: LICENSE
Requires-Dist: click==8.3.0
Requires-Dist: tabulate==0.9.0
Requires-Dist: PyYAML==6.0.2
Requires-Dist: requests==2.32.4
Requires-Dist: prettytable==3.16.0
Requires-Dist: shellingham==1.5.4
Dynamic: license-file
